RTS_DocsBuilder/RInitiate.py
RTS_DocsBuilder/__init__.py
RTS_DocsBuilder/doclayout.py
RTS_DocsBuilder/srcFolder/__init__.py
RTS_DocsBuilder/srcFolder/downpointer.svg
RTS_DocsBuilder/srcFolder/leftpointer.svg
RTS_DocsBuilder/srcFolder/rightpointer.svg
RTS_DocsBuilder-0.5.dist-info/LICENCE
RTS_DocsBuilder-0.5.dist-info/METADATA
RTS_DocsBuilder-0.5.dist-info/WHEEL
RTS_DocsBuilder-0.5.dist-info/top_level.txt
RTS_DocsBuilder-0.5.dist-info/RECORD
